base_scrapy_project/__init__.py
base_scrapy_project/exporters.py
base_scrapy_project/items.py
base_scrapy_project/pipelines.py
base_scrapy_project/settings.py
crawlutils/__init__.py
crawlutils/exporters.py
crawlutils/items.py
crawlutils/pipelines.py
crawlutils/settings.py
crawlutils/base_spiders/__init__.py
crawlutils/base_spiders/base.py
crwutils/__init__.py
crwutils/exporters.py
crwutils/items.py
crwutils/pipelines.py
crwutils/settings.py
crwutils/base_spiders/__init__.py
crwutils/base_spiders/base.py
scrapybase/__init__.py
scrapybase/exporters.py
scrapybase/items.py
scrapybase/pipelines.py
scrapybase/settings.py
scrapybase/base_spiders/__init__.py
scrapybase/base_spiders/base.py
scrapybase/spiders/__init__.py
scrapybase/spiders/base.py
crwutils-1.3.0.dist-info/LICENSE
crwutils-1.3.0.dist-info/METADATA
crwutils-1.3.0.dist-info/WHEEL
crwutils-1.3.0.dist-info/top_level.txt
crwutils-1.3.0.dist-info/RECORD
